drf_action_kit/__init__.py
drf_action_kit/action_serializer.py
drf_action_kit/exceptions.py
drf_action_kit-0.1.0.dist-info/licenses/LICENSE
drf_action_kit-0.1.0.dist-info/METADATA
drf_action_kit-0.1.0.dist-info/WHEEL
drf_action_kit-0.1.0.dist-info/top_level.txt
drf_action_kit-0.1.0.dist-info/RECORD
