Metadata-Version: 2.4
Name: drf-action-kit
Version: 0.1.0
Summary: DRF mixins & viewsets with action-based serializer support.
Home-page: https://github.com/erdimollahuseyin/drf-action-kit
Author: Erdi Mollahüseyinoğlu
Author-email: Erdi Mollahüseyinoğlu <erdimollahuseyinoglu@gmail.com>
License: MIT
Keywords: django,drf,serializers,viewset,action-based
Classifier: Programming Language :: Python :: 3
Classifier: Framework :: Django
Classifier: License :: OSI Approved :: MIT License
Classifier: Operating System :: OS Independent
Requires-Python: >=3.8
License-File: LICENSE
Requires-Dist: djangorestframework>=3.14
Dynamic: author
Dynamic: home-page
Dynamic: license-file
